pysumo/__init__.py
pysumo/pysumo.exe
pysumo-1.0.dist-info/METADATA
pysumo-1.0.dist-info/WHEEL
pysumo-1.0.dist-info/top_level.txt
pysumo-1.0.dist-info/RECORD
