Metadata-Version: 2.1
Name: pysumo
Version: 1.0
Summary: Control your parrot jumping Sumo!
Home-page: UNKNOWN
Author: DEFRETIERE Clement
Author-email: pysumo@gmail.com
License: MIT
Platform: UNKNOWN
Requires-Dist: python-socketio
Requires-Dist: urllib3
